pymcp_sse/__init__.py
pymcp_sse/client/__init__.py
pymcp_sse/client/base.py
pymcp_sse/client/llm.py
pymcp_sse/client/multi.py
pymcp_sse/common/__init__.py
pymcp_sse/common/constants.py
pymcp_sse/common/exceptions.py
pymcp_sse/common/models.py
pymcp_sse/common/utils.py
pymcp_sse/server/__init__.py
pymcp_sse/server/base.py
pymcp_sse/server/notifications.py
pymcp_sse/utils/__init__.py
pymcp_sse/utils/log_setup.py
pymcp_sse-0.4.0.dist-info/licenses/LICENSE
pymcp_sse-0.4.0.dist-info/METADATA
pymcp_sse-0.4.0.dist-info/WHEEL
pymcp_sse-0.4.0.dist-info/top_level.txt
pymcp_sse-0.4.0.dist-info/RECORD
