Metadata-Version: 2.4
Name: pymcp-sse
Version: 0.4.0
Summary: A lightweight, flexible implementation of the Model Context Protocol (MCP) for Python applications, specializing in robust HTTP/SSE transport.
Author-email: Rafaello Virgilli <rvirgilli@gmail.com>
Project-URL: Repository, https://github.com/rvirgilli/pymcp-sse
Project-URL: Bug Tracker, https://github.com/rvirgilli/pymcp-sse/issues
Keywords: mcp,model context protocol,sse,server sent events,llm,agent
Classifier: Programming Language :: Python :: 3
Classifier: License :: OSI Approved :: MIT License
Classifier: Operating System :: OS Independent
Classifier: Topic :: Communications
Classifier: Topic :: Software Development :: Libraries :: Python Modules
Requires-Python: >=3.8
License-File: LICENSE
Requires-Dist: fastapi>=0.95.0
Requires-Dist: uvicorn>=0.22.0
Requires-Dist: sse-starlette>=1.6.1
Requires-Dist: httpx>=0.24.0
Requires-Dist: httpx-sse>=0.3.1
Requires-Dist: pydantic>=2.0.0
Dynamic: license-file
